calculator_sj/__init__.py
calculator_sj-0.0.1.dist-info/LICENSE.txt
calculator_sj-0.0.1.dist-info/METADATA
calculator_sj-0.0.1.dist-info/WHEEL
calculator_sj-0.0.1.dist-info/top_level.txt
calculator_sj-0.0.1.dist-info/RECORD
