Metadata-Version: 2.1
Name: calculator-sj
Version: 0.0.1
Summary: This is a simple calculator
Author: Subhash Jadhav
Author-email: subhash.jadhav@bluepineapple.io
Classifier: Programming Language :: Python :: 3
Classifier: License :: OSI Approved :: MIT License
Classifier: Operating System :: OS Independent
License-File: LICENSE.txt
